async_pipeline/__init__.py
async_pipeline/pipe.py
async_pipeline/queue.py
async_pipeline/signal.py
async_pipeline/stage.py
async_pipeline/api/__init__.py
async_pipeline/api/concat.py
async_pipeline/api/data.py
async_pipeline/api/flatten.py
async_pipeline/api/result.py
async_pipeline/api/distribute/__init__.py
async_pipeline/api/distribute/multiply.py
async_pipeline/api/distribute/partition.py
async_pipeline/api/select/__init__.py
async_pipeline/api/select/each.py
async_pipeline/api/select/map.py
async_pipeline/api/select/peek.py
async_pipeline/api/where/__init__.py
async_pipeline/api/where/distinct.py
async_pipeline/api/where/duplicate.py
async_pipeline/api/where/filter.py
async_pipeline/api/where/filter_not.py
async_pipeline/api/where/limit.py
async_pipeline-0.1.2.dist-info/LICENSE
async_pipeline-0.1.2.dist-info/METADATA
async_pipeline-0.1.2.dist-info/WHEEL
async_pipeline-0.1.2.dist-info/top_level.txt
async_pipeline-0.1.2.dist-info/RECORD
