Metadata-Version: 2.1
Name: async_pipeline
Version: 0.1.2
Summary: Async pipeline with functional methods
Home-page: https://github.com/RockeyDon/async_pipeline
Author: Rockey Don
Author-email: bjxdrj@gmail.com
Keywords: async,pipeline,functional
Classifier: Development Status :: 4 - Beta
Classifier: Intended Audience :: Developers
Classifier: Topic :: Software Development :: Libraries :: Python Modules
Classifier: License :: OSI Approved :: MIT License
Classifier: Programming Language :: Python :: 3.7
Classifier: Programming Language :: Python :: 3.8
Classifier: Programming Language :: Python :: 3.9
Classifier: Programming Language :: Python :: 3.10
Requires-Python: >=3.7, <3.11
License-File: LICENSE
